hangman/Words.dat
hangman/__init__.py
hangman/data.py
hangman/efx.py
hangman/game.py
hangman/sides.py
hangman/start.py
hanggman-1.0.0.dist-info/LICENSE
hanggman-1.0.0.dist-info/METADATA
hanggman-1.0.0.dist-info/WHEEL
hanggman-1.0.0.dist-info/entry_points.txt
hanggman-1.0.0.dist-info/top_level.txt
hanggman-1.0.0.dist-info/RECORD
